{"Carrera Profesional": [{"año": 2022, "[<15]": 0.0, "[16-17]": 20.83, "[18-20]": 57.99, "[21-25]": 16.92, "[26<]": 4.26, "[<15]_cantidad": 1, "[16-17]_cantidad": 8378, "[18-20]_cantidad": 23328, "[21-25]_cantidad": 6807, "[26<]_cantidad": 1715}, {"año": 2023, "[<15]": 0.0, "[16-17]": 16.72, "[18-20]": 61.68, "[21-25]": 17.82, "[26<]": 3.78, "[<15]_cantidad": 1, "[16-17]_cantidad": 6859, "[18-20]_cantidad": 25303, "[21-25]_cantidad": 7311, "[26<]_cantidad": 1551}, {"año": 2024, "[<15]": 0.0, "[16-17]": 12.84, "[18-20]": 65.75, "[21-25]": 17.97, "[26<]": 3.45, "[<15]_cantidad": 0, "[16-17]_cantidad": 5337, "[18-20]_cantidad": 27331, "[21-25]_cantidad": 7469, "[26<]_cantidad": 1434}, {"año": 2025, "[<15]": 0.0, "[16-17]": 12.27, "[18-20]": 68.28, "[21-25]": 16.42, "[26<]": 3.03, "[<15]_cantidad": 1, "[16-17]_cantidad": 4945, "[18-20]_cantidad": 27508, "[21-25]_cantidad": 6613, "[26<]_cantidad": 1219}], "Segunda Especialidad": [{"año": 2022, "[<15]": 0.0, "[16-17]": 0.0, "[18-20]": 0.0, "[21-25]": 1.42, "[26<]": 98.58, "[<15]_cantidad": 0, "[16-17]_cantidad": 0, "[18-20]_cantidad": 0, "[21-25]_cantidad": 6, "[26<]_cantidad": 416}], "Maestría": [{"año": 2022, "[<15]": 0.0, "[16-17]": 0.0, "[18-20]": 0.0, "[21-25]": 14.15, "[26<]": 85.85, "[<15]_cantidad": 0, "[16-17]_cantidad": 0, "[18-20]_cantidad": 0, "[21-25]_cantidad": 328, "[26<]_cantidad": 1990}, {"año": 2024, "[<15]": 0.0, "[16-17]": 0.0, "[18-20]": 0.0, "[21-25]": 20.84, "[26<]": 79.16, "[<15]_cantidad": 0, "[16-17]_cantidad": 0, "[18-20]_cantidad": 0, "[21-25]_cantidad": 514, "[26<]_cantidad": 1952}], "Doctorado": [{"año": 2022, "[<15]": 0.0, "[16-17]": 0.0, "[18-20]": 0.0, "[21-25]": 0.95, "[26<]": 99.05, "[<15]_cantidad": 0, "[16-17]_cantidad": 0, "[18-20]_cantidad": 0, "[21-25]_cantidad": 4, "[26<]_cantidad": 417}, {"año": 2024, "[<15]": 0.0, "[16-17]": 0.0, "[18-20]": 0.0, "[21-25]": 1.91, "[26<]": 98.09, "[<15]_cantidad": 0, "[16-17]_cantidad": 0, "[18-20]_cantidad": 0, "[21-25]_cantidad": 8, "[26<]_cantidad": 410}]}