{"Carrera Profesional": [{"año": 2022, "Femenino": 56.54, "Masculino": 43.46, "Femenino_cantidad": 3312, "Masculino_cantidad": 2546}, {"año": 2023, "Femenino": 54.44, "Masculino": 45.56, "Femenino_cantidad": 3510, "Masculino_cantidad": 2937}, {"año": 2024, "Femenino": 52.42, "Masculino": 47.58, "Femenino_cantidad": 2873, "Masculino_cantidad": 2608}, {"año": 2025, "Femenino": 57.31, "Masculino": 42.69, "Femenino_cantidad": 2788, "Masculino_cantidad": 2077}], "Segunda Especialidad": [], "Maestría": [{"año": 2022, "Femenino": 51.52, "Masculino": 48.48, "Femenino_cantidad": 34, "Masculino_cantidad": 32}, {"año": 2024, "Femenino": 49.64, "Masculino": 50.36, "Femenino_cantidad": 68, "Masculino_cantidad": 69}], "Doctorado": []}